<?xml version="1.0" encoding="UTF-8"?>
<objects serializationModel="Studio.01.10.00">
    <object class="ParameterPreset" id="{309c3b1d-4d06-4611-9263-a165b37a1570}">
        <property name="name">
            <value>Start</value>
        </property>
        <relationship name="folder">
            <destination>{bd514e56-74ef-090b-1de8-385b6e662c9b}</destination>
        </relationship>
        <relationship name="parameter">
            <destination>{22963682-f7d7-4e01-91ba-8fd16e4f9fac}</destination>
        </relationship>
    </object>
    <object class="GameParameter" id="{22963682-f7d7-4e01-91ba-8fd16e4f9fac}">
        <property name="initialValue">
            <value>0</value>
        </property>
    </object>
</objects>
