<?xml version="1.0" encoding="UTF-8"?>
<objects serializationModel="Studio.01.10.00">
    <object class="Event" id="{00c6503c-1561-4f50-9abc-52430657df2e}">
        <property name="name">
            <value>Nested Event</value>
        </property>
        <property name="outputFormat">
            <value>1</value>
        </property>
        <relationship name="folder">
            <destination>{b420c766-bb46-4080-85c7-503a1242a67b}</destination>
        </relationship>
        <relationship name="mixer">
            <destination>{64f3a9e6-24ba-4a6f-b59c-ce9cc51930b3}</destination>
        </relationship>
        <relationship name="masterTrack">
            <destination>{9999f0dc-da66-4dbf-a0e7-f5396abc7093}</destination>
        </relationship>
        <relationship name="mixerInput">
            <destination>{b3ac0952-9b7a-4806-9d77-d9b2b9319579}</destination>
        </relationship>
        <relationship name="automatableProperties">
            <destination>{7118227d-edf5-4598-9013-4a561b707125}</destination>
        </relationship>
        <relationship name="markerTracks">
            <destination>{6de146ed-e189-4f79-8cea-13684d3baf2f}</destination>
        </relationship>
        <relationship name="groupTracks">
            <destination>{caa581e9-da6d-4f08-9242-7815302c8ee2}</destination>
        </relationship>
        <relationship name="timeline">
            <destination>{dbb79048-b2bf-4ed3-8d1b-1454555d7476}</destination>
        </relationship>
    </object>
    <object class="EventMixer" id="{64f3a9e6-24ba-4a6f-b59c-ce9cc51930b3}">
        <relationship name="masterBus">
            <destination>{7ac25285-36b5-45f0-90e1-50d6443354b6}</destination>
        </relationship>
    </object>
    <object class="MasterTrack" id="{9999f0dc-da66-4dbf-a0e7-f5396abc7093}">
        <relationship name="mixerGroup">
            <destination>{7ac25285-36b5-45f0-90e1-50d6443354b6}</destination>
        </relationship>
    </object>
    <object class="MixerInput" id="{b3ac0952-9b7a-4806-9d77-d9b2b9319579}">
        <relationship name="effectChain">
            <destination>{0c282498-1fcd-4358-8fc3-5a7c0a80d226}</destination>
        </relationship>
        <relationship name="panner">
            <destination>{24b916da-fd13-4a06-857f-035aac78d582}</destination>
        </relationship>
    </object>
    <object class="EventAutomatableProperties" id="{7118227d-edf5-4598-9013-4a561b707125}"/>
    <object class="MarkerTrack" id="{6de146ed-e189-4f79-8cea-13684d3baf2f}"/>
    <object class="GroupTrack" id="{caa581e9-da6d-4f08-9242-7815302c8ee2}">
        <relationship name="modules">
            <destination>{1416582b-662a-41fb-ba99-1af4a3018667}</destination>
        </relationship>
        <relationship name="mixerGroup">
            <destination>{6b8ab089-73f8-42cc-95bc-ae9d95cfed03}</destination>
        </relationship>
    </object>
    <object class="Timeline" id="{dbb79048-b2bf-4ed3-8d1b-1454555d7476}">
        <relationship name="modules">
            <destination>{1416582b-662a-41fb-ba99-1af4a3018667}</destination>
        </relationship>
        <relationship name="markers">
            <destination>{99c8329d-caac-4948-b452-e62db513b653}</destination>
        </relationship>
    </object>
    <object class="EventMixerMaster" id="{7ac25285-36b5-45f0-90e1-50d6443354b6}">
        <relationship name="effectChain">
            <destination>{9a254dfe-22ad-4eae-a0b1-ef42c8d46792}</destination>
        </relationship>
        <relationship name="panner">
            <destination>{48280a1e-7028-4cff-ad82-14d1332b17e4}</destination>
        </relationship>
        <relationship name="mixer">
            <destination>{64f3a9e6-24ba-4a6f-b59c-ce9cc51930b3}</destination>
        </relationship>
    </object>
    <object class="MixerBusEffectChain" id="{0c282498-1fcd-4358-8fc3-5a7c0a80d226}">
        <relationship name="effects">
            <destination>{7ebcb586-d814-478a-a157-6d3d658ff3e4}</destination>
        </relationship>
    </object>
    <object class="MixerBusPanner" id="{24b916da-fd13-4a06-857f-035aac78d582}"/>
    <object class="SingleSound" id="{1416582b-662a-41fb-ba99-1af4a3018667}">
        <property name="length">
            <value>102.40000000000001</value>
        </property>
        <property name="looping">
            <value>true</value>
        </property>
        <relationship name="audioFile">
            <destination>{f8852a64-b9f9-4361-9b51-ae14872934b2}</destination>
        </relationship>
    </object>
    <object class="EventMixerGroup" id="{6b8ab089-73f8-42cc-95bc-ae9d95cfed03}">
        <property name="name">
            <value>Audio 1</value>
        </property>
        <relationship name="effectChain">
            <destination>{6d4c4fbe-851d-4e88-8e9a-790e2588f93d}</destination>
        </relationship>
        <relationship name="panner">
            <destination>{8a9242d0-8086-423b-9f84-b14a10d0d36f}</destination>
        </relationship>
        <relationship name="output">
            <destination>{7ac25285-36b5-45f0-90e1-50d6443354b6}</destination>
        </relationship>
    </object>
    <object class="LoopRegion" id="{99c8329d-caac-4948-b452-e62db513b653}">
        <property name="position">
            <value>0</value>
        </property>
        <property name="length">
            <value>102.40000000000001</value>
        </property>
        <relationship name="timeline">
            <destination>{dbb79048-b2bf-4ed3-8d1b-1454555d7476}</destination>
        </relationship>
        <relationship name="markerTrack">
            <destination>{6de146ed-e189-4f79-8cea-13684d3baf2f}</destination>
        </relationship>
    </object>
    <object class="MixerBusEffectChain" id="{9a254dfe-22ad-4eae-a0b1-ef42c8d46792}">
        <relationship name="effects">
            <destination>{b8614fe0-9858-490f-8669-738b103b9aab}</destination>
        </relationship>
    </object>
    <object class="MixerBusPanner" id="{48280a1e-7028-4cff-ad82-14d1332b17e4}"/>
    <object class="MixerBusFader" id="{7ebcb586-d814-478a-a157-6d3d658ff3e4}"/>
    <object class="MixerBusEffectChain" id="{6d4c4fbe-851d-4e88-8e9a-790e2588f93d}">
        <relationship name="effects">
            <destination>{848ca50c-377f-4b75-9d75-ab72afbeb1aa}</destination>
        </relationship>
    </object>
    <object class="MixerBusPanner" id="{8a9242d0-8086-423b-9f84-b14a10d0d36f}"/>
    <object class="MixerBusFader" id="{b8614fe0-9858-490f-8669-738b103b9aab}"/>
    <object class="MixerBusFader" id="{848ca50c-377f-4b75-9d75-ab72afbeb1aa}"/>
</objects>
