<?xml version="1.0" encoding="UTF-8"?>
<objects serializationModel="Studio.01.10.00">
    <object class="Event" id="{c3e6363a-e71b-4aba-91b1-2ddc67f6bca9}">
        <property name="name">
            <value>Nested Event (7)</value>
        </property>
        <property name="outputFormat">
            <value>1</value>
        </property>
        <relationship name="folder">
            <destination>{381d07c7-0cee-4f6a-b93f-d28daa210135}</destination>
        </relationship>
        <relationship name="mixer">
            <destination>{4bfddb42-75ae-44e8-aac0-c5af2068272d}</destination>
        </relationship>
        <relationship name="masterTrack">
            <destination>{fd14efa8-04c1-400d-92cc-405ef1e47dd5}</destination>
        </relationship>
        <relationship name="mixerInput">
            <destination>{3bc53210-f68e-4703-a1b6-acc2ae8009e2}</destination>
        </relationship>
        <relationship name="automatableProperties">
            <destination>{2b9c828b-0b0a-460b-9627-ad2d79ffee40}</destination>
        </relationship>
        <relationship name="markerTracks">
            <destination>{aaf63c9d-07d2-4ec2-9064-8da935ebc8d5}</destination>
        </relationship>
        <relationship name="groupTracks">
            <destination>{6801b819-4605-42f9-8dbe-e6a7c7aec8c2}</destination>
            <destination>{d0a41638-9e1c-43b0-a738-d0418cd2cf33}</destination>
        </relationship>
        <relationship name="timeline">
            <destination>{e0b23df6-9b6c-4e07-9362-2bf7d56cc943}</destination>
        </relationship>
    </object>
    <object class="EventMixer" id="{4bfddb42-75ae-44e8-aac0-c5af2068272d}">
        <relationship name="masterBus">
            <destination>{37ff97fe-d623-48a5-b600-594b7b064f00}</destination>
        </relationship>
    </object>
    <object class="MasterTrack" id="{fd14efa8-04c1-400d-92cc-405ef1e47dd5}">
        <relationship name="mixerGroup">
            <destination>{37ff97fe-d623-48a5-b600-594b7b064f00}</destination>
        </relationship>
    </object>
    <object class="MixerInput" id="{3bc53210-f68e-4703-a1b6-acc2ae8009e2}">
        <relationship name="effectChain">
            <destination>{aa9f9696-cd14-43c3-a35e-143caee45570}</destination>
        </relationship>
        <relationship name="panner">
            <destination>{226c1879-fec7-450f-af6b-b702f8f50411}</destination>
        </relationship>
    </object>
    <object class="EventAutomatableProperties" id="{2b9c828b-0b0a-460b-9627-ad2d79ffee40}"/>
    <object class="MarkerTrack" id="{aaf63c9d-07d2-4ec2-9064-8da935ebc8d5}"/>
    <object class="GroupTrack" id="{6801b819-4605-42f9-8dbe-e6a7c7aec8c2}">
        <relationship name="modules">
            <destination>{eeac0d4e-4095-4a89-a36d-4a933652042a}</destination>
        </relationship>
        <relationship name="mixerGroup">
            <destination>{a385640a-df2f-4342-981f-1ffef8b0dcb1}</destination>
        </relationship>
    </object>
    <object class="GroupTrack" id="{d0a41638-9e1c-43b0-a738-d0418cd2cf33}">
        <relationship name="modules">
            <destination>{3e670e04-a0b1-49aa-8ed6-cc544f6d13bc}</destination>
        </relationship>
        <relationship name="mixerGroup">
            <destination>{b740029e-fa7d-48b2-a24b-1f5e992ba0b6}</destination>
        </relationship>
    </object>
    <object class="Timeline" id="{e0b23df6-9b6c-4e07-9362-2bf7d56cc943}">
        <relationship name="modules">
            <destination>{eeac0d4e-4095-4a89-a36d-4a933652042a}</destination>
            <destination>{3e670e04-a0b1-49aa-8ed6-cc544f6d13bc}</destination>
        </relationship>
    </object>
    <object class="EventMixerMaster" id="{37ff97fe-d623-48a5-b600-594b7b064f00}">
        <relationship name="effectChain">
            <destination>{38f7fa49-cdf6-45c8-a24a-66b87f26e9f1}</destination>
        </relationship>
        <relationship name="panner">
            <destination>{46754e86-6799-4da4-a4cf-8d9468dbe51f}</destination>
        </relationship>
        <relationship name="mixer">
            <destination>{4bfddb42-75ae-44e8-aac0-c5af2068272d}</destination>
        </relationship>
    </object>
    <object class="MixerBusEffectChain" id="{aa9f9696-cd14-43c3-a35e-143caee45570}">
        <relationship name="effects">
            <destination>{fdf22af7-b67b-47ea-bb2e-653f51d41b84}</destination>
        </relationship>
    </object>
    <object class="MixerBusPanner" id="{226c1879-fec7-450f-af6b-b702f8f50411}"/>
    <object class="SingleSound" id="{eeac0d4e-4095-4a89-a36d-4a933652042a}">
        <property name="length">
            <value>41.379066026552039</value>
        </property>
        <property name="timelockedOffset">
            <value>60.000267306781296</value>
        </property>
        <relationship name="audioFile">
            <destination>{a08af1ef-852e-403e-ae2b-fdecd2e1bc10}</destination>
        </relationship>
    </object>
    <object class="EventMixerGroup" id="{a385640a-df2f-4342-981f-1ffef8b0dcb1}">
        <property name="name">
            <value>Audio 1</value>
        </property>
        <relationship name="effectChain">
            <destination>{b2fdb203-fe3f-42a0-b630-9260b9a1ecc6}</destination>
        </relationship>
        <relationship name="panner">
            <destination>{d3b5ee07-2710-42a6-b9e0-3769ac83c619}</destination>
        </relationship>
        <relationship name="output">
            <destination>{37ff97fe-d623-48a5-b600-594b7b064f00}</destination>
        </relationship>
    </object>
    <object class="SingleSound" id="{3e670e04-a0b1-49aa-8ed6-cc544f6d13bc}">
        <property name="length">
            <value>41.379066026552081</value>
        </property>
        <property name="timelockedOffset">
            <value>60.00026730678124</value>
        </property>
        <relationship name="audioFile">
            <destination>{362dfcd1-4115-46a6-aba7-d93e36eb618b}</destination>
        </relationship>
    </object>
    <object class="EventMixerGroup" id="{b740029e-fa7d-48b2-a24b-1f5e992ba0b6}">
        <property name="name">
            <value>Audio 2</value>
        </property>
        <relationship name="effectChain">
            <destination>{7f16aacf-ae9d-4612-b641-3d63ed53f8a3}</destination>
        </relationship>
        <relationship name="panner">
            <destination>{4e9859e6-c155-4a7b-9c88-e167b0f5be9d}</destination>
        </relationship>
        <relationship name="output">
            <destination>{37ff97fe-d623-48a5-b600-594b7b064f00}</destination>
        </relationship>
    </object>
    <object class="MixerBusEffectChain" id="{38f7fa49-cdf6-45c8-a24a-66b87f26e9f1}">
        <relationship name="effects">
            <destination>{edd2a1e1-3a65-4e0f-9d6f-08879dc7ade5}</destination>
        </relationship>
    </object>
    <object class="MixerBusPanner" id="{46754e86-6799-4da4-a4cf-8d9468dbe51f}"/>
    <object class="MixerBusFader" id="{fdf22af7-b67b-47ea-bb2e-653f51d41b84}"/>
    <object class="MixerBusEffectChain" id="{b2fdb203-fe3f-42a0-b630-9260b9a1ecc6}">
        <relationship name="effects">
            <destination>{10afdbd1-b19b-4a8d-9105-8652c11012b9}</destination>
        </relationship>
    </object>
    <object class="MixerBusPanner" id="{d3b5ee07-2710-42a6-b9e0-3769ac83c619}"/>
    <object class="MixerBusEffectChain" id="{7f16aacf-ae9d-4612-b641-3d63ed53f8a3}">
        <relationship name="effects">
            <destination>{6b37fc72-bb53-47c6-96c2-b30dedb06b09}</destination>
        </relationship>
    </object>
    <object class="MixerBusPanner" id="{4e9859e6-c155-4a7b-9c88-e167b0f5be9d}"/>
    <object class="MixerBusFader" id="{edd2a1e1-3a65-4e0f-9d6f-08879dc7ade5}"/>
    <object class="MixerBusFader" id="{10afdbd1-b19b-4a8d-9105-8652c11012b9}"/>
    <object class="MixerBusFader" id="{6b37fc72-bb53-47c6-96c2-b30dedb06b09}"/>
</objects>
