<?xml version="1.0" encoding="UTF-8"?>
<objects serializationModel="Studio.01.10.00">
    <object class="Event" id="{e8fbb01f-7b4d-4dc2-aa98-7b27e14329ac}">
        <property name="name">
            <value>Nested Event</value>
        </property>
        <property name="outputFormat">
            <value>0</value>
        </property>
        <relationship name="folder">
            <destination>{92aaa2f6-4e3c-4db4-94e7-15b5fb786b93}</destination>
        </relationship>
        <relationship name="mixer">
            <destination>{5827f9c5-e441-451a-982d-aea920d28745}</destination>
        </relationship>
        <relationship name="masterTrack">
            <destination>{897484b6-984a-4fca-9dd3-8e48ec27c7b3}</destination>
        </relationship>
        <relationship name="mixerInput">
            <destination>{b045a819-4360-4b83-8c3b-f86b5ef5c32b}</destination>
        </relationship>
        <relationship name="automatableProperties">
            <destination>{c14b5643-2e63-4183-898c-6efe82fe74c8}</destination>
        </relationship>
        <relationship name="markerTracks">
            <destination>{9d7d0c89-bb6b-4791-ba6b-f5359d82b24b}</destination>
        </relationship>
        <relationship name="groupTracks">
            <destination>{e9499a4e-44a5-4f47-a910-9d4681012622}</destination>
        </relationship>
        <relationship name="timeline">
            <destination>{e6d5e994-9897-48f2-906c-fb638df6d459}</destination>
        </relationship>
    </object>
    <object class="EventMixer" id="{5827f9c5-e441-451a-982d-aea920d28745}">
        <relationship name="masterBus">
            <destination>{8d3cd2f2-d72a-4e70-8a06-9ab4c55480f3}</destination>
        </relationship>
    </object>
    <object class="MasterTrack" id="{897484b6-984a-4fca-9dd3-8e48ec27c7b3}">
        <relationship name="mixerGroup">
            <destination>{8d3cd2f2-d72a-4e70-8a06-9ab4c55480f3}</destination>
        </relationship>
    </object>
    <object class="MixerInput" id="{b045a819-4360-4b83-8c3b-f86b5ef5c32b}">
        <relationship name="effectChain">
            <destination>{d9d1c7ab-c649-4f41-9f04-1cd48423a6cf}</destination>
        </relationship>
        <relationship name="panner">
            <destination>{4e2d21b7-fef7-4e61-b4b7-5a7265c8efb2}</destination>
        </relationship>
    </object>
    <object class="EventAutomatableProperties" id="{c14b5643-2e63-4183-898c-6efe82fe74c8}"/>
    <object class="MarkerTrack" id="{9d7d0c89-bb6b-4791-ba6b-f5359d82b24b}"/>
    <object class="GroupTrack" id="{e9499a4e-44a5-4f47-a910-9d4681012622}">
        <relationship name="modules">
            <destination>{69d0f1c5-13e2-40f8-9d55-2434e1e775bc}</destination>
        </relationship>
        <relationship name="mixerGroup">
            <destination>{540d57fc-4121-46a7-887a-bebd3c196b29}</destination>
        </relationship>
    </object>
    <object class="Timeline" id="{e6d5e994-9897-48f2-906c-fb638df6d459}">
        <relationship name="modules">
            <destination>{69d0f1c5-13e2-40f8-9d55-2434e1e775bc}</destination>
        </relationship>
    </object>
    <object class="EventMixerMaster" id="{8d3cd2f2-d72a-4e70-8a06-9ab4c55480f3}">
        <relationship name="effectChain">
            <destination>{2cbaeb10-a5d7-4835-be10-35c484c9429e}</destination>
        </relationship>
        <relationship name="panner">
            <destination>{27b94810-87ab-44c6-a3b3-00f01bf02213}</destination>
        </relationship>
        <relationship name="mixer">
            <destination>{5827f9c5-e441-451a-982d-aea920d28745}</destination>
        </relationship>
    </object>
    <object class="MixerBusEffectChain" id="{d9d1c7ab-c649-4f41-9f04-1cd48423a6cf}">
        <relationship name="effects">
            <destination>{5abf3763-baff-4b7f-8c80-df5bce7f7b11}</destination>
        </relationship>
    </object>
    <object class="MixerBusPanner" id="{4e2d21b7-fef7-4e61-b4b7-5a7265c8efb2}"/>
    <object class="MultiSound" id="{69d0f1c5-13e2-40f8-9d55-2434e1e775bc}">
        <property name="triggerProbability">
            <value>50.5</value>
        </property>
        <property name="isAsync">
            <value>true</value>
        </property>
        <property name="length">
            <value>6.5</value>
        </property>
        <relationship name="modulators">
            <destination>{36f702aa-2428-4562-8687-2c2eb0b59fab}</destination>
            <destination>{9dc12a33-f9a5-47ba-bb75-bbc0828e981a}</destination>
        </relationship>
        <relationship name="sounds">
            <destination>{bdc80196-2d83-4ce6-9384-137444acdee2}</destination>
            <destination>{52c49145-20d6-49e4-bd46-bb16e709c907}</destination>
            <destination>{5fdca8f9-1316-40b4-bb70-6fbf2db55153}</destination>
            <destination>{b70f4b51-21e9-4e26-bbbb-f78c29662366}</destination>
        </relationship>
    </object>
    <object class="EventMixerGroup" id="{540d57fc-4121-46a7-887a-bebd3c196b29}">
        <property name="name">
            <value>Audio 1</value>
        </property>
        <relationship name="effectChain">
            <destination>{27712ad5-0d1a-4b30-a6e7-f7557ab3e4cb}</destination>
        </relationship>
        <relationship name="panner">
            <destination>{65838a8e-a186-47a8-a189-1f139f4db66b}</destination>
        </relationship>
        <relationship name="output">
            <destination>{8d3cd2f2-d72a-4e70-8a06-9ab4c55480f3}</destination>
        </relationship>
    </object>
    <object class="MixerBusEffectChain" id="{2cbaeb10-a5d7-4835-be10-35c484c9429e}">
        <relationship name="effects">
            <destination>{d581baba-9223-4b7c-80a5-9bf1601696ca}</destination>
        </relationship>
    </object>
    <object class="MixerBusPanner" id="{27b94810-87ab-44c6-a3b3-00f01bf02213}"/>
    <object class="MixerBusFader" id="{5abf3763-baff-4b7f-8c80-df5bce7f7b11}"/>
    <object class="RandomizerModulator" id="{36f702aa-2428-4562-8687-2c2eb0b59fab}">
        <property name="nameOfPropertyBeingModulated">
            <value>pitch</value>
        </property>
        <property name="amount">
            <value>3</value>
        </property>
    </object>
    <object class="RandomizerModulator" id="{9dc12a33-f9a5-47ba-bb75-bbc0828e981a}">
        <property name="nameOfPropertyBeingModulated">
            <value>volume</value>
        </property>
        <property name="amount">
            <value>3.60000014</value>
        </property>
    </object>
    <object class="SingleSound" id="{bdc80196-2d83-4ce6-9384-137444acdee2}">
        <relationship name="audioFile">
            <destination>{7191e9a4-20e2-40c1-b7da-f0629edc12b3}</destination>
        </relationship>
    </object>
    <object class="SingleSound" id="{52c49145-20d6-49e4-bd46-bb16e709c907}">
        <relationship name="audioFile">
            <destination>{190b6636-68d0-4f5a-a4a1-121dfc83f098}</destination>
        </relationship>
    </object>
    <object class="SingleSound" id="{5fdca8f9-1316-40b4-bb70-6fbf2db55153}">
        <relationship name="audioFile">
            <destination>{40cbb9dc-f3e7-4aba-81a0-e46f74a07fe9}</destination>
        </relationship>
    </object>
    <object class="SingleSound" id="{b70f4b51-21e9-4e26-bbbb-f78c29662366}">
        <relationship name="audioFile">
            <destination>{6f727b81-f59c-4dc2-b79f-84d5946f6b6d}</destination>
        </relationship>
    </object>
    <object class="MixerBusEffectChain" id="{27712ad5-0d1a-4b30-a6e7-f7557ab3e4cb}">
        <relationship name="effects">
            <destination>{37216309-97cb-4ed1-8b4f-358ded195ce0}</destination>
        </relationship>
    </object>
    <object class="MixerBusPanner" id="{65838a8e-a186-47a8-a189-1f139f4db66b}"/>
    <object class="MixerBusFader" id="{d581baba-9223-4b7c-80a5-9bf1601696ca}"/>
    <object class="MixerBusFader" id="{37216309-97cb-4ed1-8b4f-358ded195ce0}"/>
</objects>
