<?xml version="1.0" encoding="UTF-8"?>
<objects serializationModel="Studio.01.09.00">
    <object class="AudioFile" id="{39f06b00-7d57-4526-a630-be8526d14a6f}">
        <property name="assetPath">
            <value>Troll/Footsteps/Wood/Land/Troll_land_wood_02.wav</value>
        </property>
        <property name="frequencyInKHz">
            <value>48</value>
        </property>
        <property name="channelCount">
            <value>2</value>
        </property>
        <property name="length">
            <value>0.56177083333333333</value>
        </property>
        <relationship name="masterAssetFolder">
            <destination>{4cf0234a-aea2-4257-9619-110ab2dd4ecd}</destination>
        </relationship>
    </object>
</objects>
