<?xml version="1.0" encoding="UTF-8"?>
<objects serializationModel="Studio.01.10.00">
    <object class="AudioFile" id="{b0621a46-b522-4536-84fa-9674516f46df}">
        <property name="assetPath">
            <value>Button_klick_bass_01.wav</value>
        </property>
        <property name="frequencyInKHz">
            <value>48</value>
        </property>
        <property name="channelCount">
            <value>2</value>
        </property>
        <property name="length">
            <value>4.4264583333333336</value>
        </property>
        <relationship name="masterAssetFolder">
            <destination>{4cf0234a-aea2-4257-9619-110ab2dd4ecd}</destination>
        </relationship>
    </object>
</objects>
