<?xml version="1.0" encoding="UTF-8"?>
<objects serializationModel="Studio.01.10.00">
    <object class="AudioFile" id="{eb6c43d0-68a0-4b4e-95a7-d5f62ca98260}">
        <property name="assetPath">
            <value>Wind_howel_loop_stereo_02.wav</value>
        </property>
        <property name="isStreaming">
            <value>true</value>
        </property>
        <property name="frequencyInKHz">
            <value>48</value>
        </property>
        <property name="channelCount">
            <value>2</value>
        </property>
        <property name="length">
            <value>53</value>
        </property>
        <relationship name="masterAssetFolder">
            <destination>{4cf0234a-aea2-4257-9619-110ab2dd4ecd}</destination>
        </relationship>
    </object>
</objects>
