<?xml version="1.0" encoding="UTF-8"?>
<objects serializationModel="Studio.01.10.00">
    <object class="MixerGroup" id="{f7c09ba2-228a-4cb3-8591-ffb86763ee8f}">
        <property name="name">
            <value>Barn</value>
        </property>
        <relationship name="effectChain">
            <destination>{a8ee8538-d84e-4819-b885-323f39c08bfe}</destination>
        </relationship>
        <relationship name="panner">
            <destination>{10906c85-49d4-4de8-818d-f2eb3c9e0bf8}</destination>
        </relationship>
        <relationship name="output">
            <destination>{bda9fff5-ea7a-42d5-a080-f191b6eee74b}</destination>
        </relationship>
    </object>
    <object class="MixerBusEffectChain" id="{a8ee8538-d84e-4819-b885-323f39c08bfe}">
        <relationship name="effects">
            <destination>{4af1ea1d-b263-4b86-aee2-5d685e5bb3f3}</destination>
            <destination>{73b70530-234c-4da2-ad1a-978f1b6b563a}</destination>
            <destination>{f0353a48-a15b-4bc1-a28d-75be7429bb06}</destination>
        </relationship>
    </object>
    <object class="MixerBusPanner" id="{10906c85-49d4-4de8-818d-f2eb3c9e0bf8}"/>
    <object class="MixerBusFader" id="{4af1ea1d-b263-4b86-aee2-5d685e5bb3f3}"/>
    <object class="MixerSend" id="{73b70530-234c-4da2-ad1a-978f1b6b563a}">
        <property name="inputFormat">
            <value>1</value>
        </property>
        <relationship name="mixerReturn">
            <destination>{0ea3b668-6aa1-481e-95f9-734b95db82f0}</destination>
        </relationship>
    </object>
    <object class="CompressorEffect" id="{f0353a48-a15b-4bc1-a28d-75be7429bb06}">
        <property name="ratio">
            <value>1.29999995</value>
        </property>
        <property name="sidechainEnabled">
            <value>true</value>
        </property>
    </object>
</objects>
